setup.py
itertools_s/__init__.py
itertools_s.egg-info/PKG-INFO
itertools_s.egg-info/SOURCES.txt
itertools_s.egg-info/dependency_links.txt
itertools_s.egg-info/not-zip-safe
itertools_s.egg-info/top_level.txt