Metadata-Version: 1.0
Name: itertools-s
Version: 0.1
Summary: Best of luck
Home-page: UNKNOWN
Author: Fatal
Author-email: fatalanonymous@gmail.com
License: MIT
Platform: UNKNOWN
